kedm/__init__.py
kedm/_kedm.cpython-314t-x86_64-linux-gnu.so
kedm_cuda12x.libs/libcudart-256e6409.so.12.9.79
kedm_cuda12x.libs/libgomp-e985bcbb.so.1.0.0
kedm_cuda12x-0.10.0.dist-info/METADATA
kedm_cuda12x-0.10.0.dist-info/WHEEL
kedm_cuda12x-0.10.0.dist-info/RECORD
kedm_cuda12x-0.10.0.dist-info/licenses/LICENSE
kedm_cuda12x-0.10.0.dist-info/licenses/LICENSE-THIRD-PARTY
kedm_cuda12x-0.10.0.dist-info/sboms/auditwheel.cdx.json
