Metadata-Version: 2.4
Name: kedm-cuda12x
Version: 0.10.0
Summary: A high-performance implementation of the Empirical Dynamic Modeling (EDM) framework
Author-Email: Keichi Takahashi <hello@keichi.dev>
License-Expression: MIT
Classifier: Programming Language :: C++
Classifier: Programming Language :: Python
Classifier: Operating System :: MacOS :: MacOS X
Classifier: Operating System :: POSIX :: Linux
Classifier: Development Status :: 4 - Beta
Classifier: Intended Audience :: Science/Research
Classifier: Topic :: Scientific/Engineering :: Mathematics
Project-URL: Homepage, https://github.com/keichi/kEDM
Project-URL: Documentation, https://kedm.readthedocs.io/
Project-URL: Repository, https://github.com/keichi/kEDM
Project-URL: Issues, https://github.com/keichi/kEDM/issues
Requires-Python: >=3.10
Requires-Dist: numpy>=1.24.0
Provides-Extra: test
Requires-Dist: pytest>=8.0.0; extra == "test"
